{"engine": "tesseract", "page": 32, "words": [{"text": "EXHIBIT", "bbox": [788, 209, 894, 228], "conf": 93.0}, {"text": "E", "bbox": [902, 209, 916, 228], "conf": 92.0}, {"text": "Landlord", "bbox": [204, 306, 308, 327], "conf": 96.0}, {"text": "will", "bbox": [318, 306, 354, 326], "conf": 96.0}, {"text": "perform", "bbox": [365, 306, 458, 332], "conf": 96.0}, {"text": "the", "bbox": [467, 306, 505, 327], "conf": 96.0}, {"text": "following", "bbox": [514, 306, 620, 332], "conf": 96.0}, {"text": "at", "bbox": [630, 307, 652, 327], "conf": 96.0}, {"text": "its", "bbox": [662, 306, 687, 327], "conf": 96.0}, {"text": "sole", "bbox": [696, 306, 746, 327], "conf": 96.0}, {"text": "cost:", "bbox": [755, 307, 811, 327], "conf": 96.0}, {"text": "Signage:", "bbox": [303, 372, 409, 398], "conf": 96.0}, {"text": "Standard", "bbox": [439, 372, 548, 392], "conf": 96.0}, {"text": "Vinyl", "bbox": [563, 372, 621, 398], "conf": 74.0}, {"text": "@", "bbox": [638, 372, 663, 398], "conf": 92.0}, {"text": "Outside", "bbox": [679, 372, 772, 392], "conf": 96.0}, {"text": "Entry", "bbox": [788, 372, 850, 398], "conf": 96.0}, {"text": "to", "bbox": [864, 373, 886, 392], "conf": 95.0}, {"text": "Common", "bbox": [901, 372, 1011, 392], "conf": 96.0}, {"text": "Corridor", "bbox": [1027, 372, 1127, 392], "conf": 96.0}, {"text": "and", "bbox": [1140, 372, 1184, 392], "conf": 96.0}, {"text": "Inside", "bbox": [1201, 372, 1272, 392], "conf": 96.0}, {"text": "Entry", "bbox": [1288, 372, 1350, 398], "conf": 96.0}, {"text": "Door,", "bbox": [1366, 372, 1429, 396], "conf": 95.0}, {"text": "ADA", "bbox": [1445, 372, 1502, 392], "conf": 96.0}, {"text": "Signage", "bbox": [303, 404, 402, 430], "conf": 95.0}, {"text": "at", "bbox": [410, 405, 432, 424], "conf": 96.0}, {"text": "Inside", "bbox": [441, 404, 511, 424], "conf": 96.0}, {"text": "Entry", "bbox": [521, 404, 583, 430], "conf": 96.0}, {"text": "Door,", "bbox": [591, 404, 655, 428], "conf": 96.0}, {"text": "2", "bbox": [664, 404, 677, 424], "conf": 96.0}, {"text": "Panels", "bbox": [686, 404, 768, 424], "conf": 96.0}, {"text": "on", "bbox": [776, 409, 804, 424], "conf": 96.0}, {"text": "Each", "bbox": [814, 404, 873, 424], "conf": 96.0}, {"text": "Monument", "bbox": [883, 404, 1012, 424], "conf": 96.0}, {"text": "Sign", "bbox": [1020, 404, 1072, 430], "conf": 96.0}, {"text": "(4", "bbox": [1081, 404, 1103, 430], "conf": 96.0}, {"text": "panels", "bbox": [1112, 404, 1191, 430], "conf": 96.0}, {"text": "total)", "bbox": [1198, 404, 1259, 430], "conf": 96.0}, {"text": "at", "bbox": [1267, 405, 1289, 424], "conf": 96.0}, {"text": "Street,", "bbox": [1296, 404, 1374, 428], "conf": 96.0}, {"text": "Company", "bbox": [1384, 404, 1501, 430], "conf": 96.0}, {"text": "Listing", "bbox": [303, 436, 380, 462], "conf": 96.0}, {"text": "at", "bbox": [390, 437, 413, 456], "conf": 96.0}, {"text": "Each", "bbox": [423, 436, 482, 456], "conf": 96.0}, {"text": "Directory", "bbox": [494, 436, 602, 462], "conf": 96.0}, {"text": "Rekey", "bbox": [304, 470, 380, 496], "conf": 93.0}, {"text": "Space", "bbox": [390, 470, 466, 496], "conf": 93.0}, {"text": "\u2014", "bbox": [475, 482, 491, 484], "conf": 90.0}, {"text": "To", "bbox": [500, 470, 531, 490], "conf": 96.0}, {"text": "Include", "bbox": [542, 470, 628, 490], "conf": 95.0}, {"text": "Keypad", "bbox": [639, 470, 730, 496], "conf": 96.0}, {"text": "on", "bbox": [741, 475, 769, 490], "conf": 95.0}, {"text": "the", "bbox": [779, 470, 816, 490], "conf": 96.0}, {"text": "Main", "bbox": [828, 470, 884, 490], "conf": 96.0}, {"text": "Entry", "bbox": [896, 470, 958, 496], "conf": 96.0}, {"text": "Door.", "bbox": [969, 470, 1032, 490], "conf": 96.0}, {"text": "Tenant", "bbox": [1052, 470, 1137, 490], "conf": 96.0}, {"text": "needs", "bbox": [1148, 470, 1220, 490], "conf": 95.0}, {"text": "to", "bbox": [1230, 471, 1252, 490], "conf": 96.0}, {"text": "let", "bbox": [1263, 470, 1290, 490], "conf": 96.0}, {"text": "Landlord", "bbox": [1300, 470, 1405, 490], "conf": 96.0}, {"text": "know", "bbox": [1417, 470, 1479, 490], "conf": 96.0}, {"text": "if", "bbox": [1490, 470, 1502, 490], "conf": 94.0}, {"text": "any", "bbox": [302, 507, 346, 528], "conf": 96.0}, {"text": "other", "bbox": [355, 502, 418, 522], "conf": 96.0}, {"text": "room", "bbox": [427, 507, 487, 522], "conf": 96.0}, {"text": "requires", "bbox": [498, 502, 595, 528], "conf": 96.0}, {"text": "a", "bbox": [605, 507, 618, 522], "conf": 92.0}, {"text": "lockset.", "bbox": [629, 502, 719, 522], "conf": 92.0}, {"text": "Install", "bbox": [304, 535, 372, 555], "conf": 96.0}, {"text": "new", "bbox": [384, 540, 432, 555], "conf": 96.0}, {"text": "laminate", "bbox": [442, 535, 544, 555], "conf": 96.0}, {"text": "kitchen", "bbox": [555, 535, 639, 555], "conf": 96.0}, {"text": "countertops.", "bbox": [650, 536, 799, 561], "conf": 96.0}, {"text": "Tenant", "bbox": [818, 535, 903, 555], "conf": 96.0}, {"text": "to", "bbox": [912, 536, 934, 555], "conf": 96.0}, {"text": "select", "bbox": [943, 535, 1015, 555], "conf": 96.0}, {"text": "the", "bbox": [1023, 535, 1060, 555], "conf": 96.0}, {"text": "laminate.", "bbox": [1070, 535, 1179, 555], "conf": 96.0}, {"text": "Install", "bbox": [304, 569, 372, 589], "conf": 96.0}, {"text": "water", "bbox": [382, 570, 450, 589], "conf": 96.0}, {"text": "line", "bbox": [459, 569, 500, 589], "conf": 96.0}, {"text": "and", "bbox": [509, 569, 553, 589], "conf": 96.0}, {"text": "outlet", "bbox": [563, 569, 630, 589], "conf": 96.0}, {"text": "for", "bbox": [638, 569, 671, 589], "conf": 96.0}, {"text": "refrigerator.", "bbox": [680, 569, 819, 595], "conf": 96.0}, {"text": "Replace", "bbox": [304, 603, 402, 629], "conf": 95.0}, {"text": "kitchen", "bbox": [413, 603, 497, 623], "conf": 95.0}, {"text": "vinyl", "bbox": [507, 603, 561, 629], "conf": 96.0}, {"text": "composition", "bbox": [571, 603, 716, 629], "conf": 96.0}, {"text": "tile.", "bbox": [726, 603, 767, 623], "conf": 96.0}, {"text": "Replace", "bbox": [304, 637, 402, 663], "conf": 96.0}, {"text": "ceiling", "bbox": [419, 637, 495, 663], "conf": 96.0}, {"text": "tiles", "bbox": [512, 637, 560, 657], "conf": 96.0}, {"text": "in", "bbox": [578, 637, 596, 657], "conf": 96.0}, {"text": "open", "bbox": [613, 642, 672, 663], "conf": 96.0}, {"text": "work", "bbox": [690, 637, 748, 657], "conf": 96.0}, {"text": "area", "bbox": [764, 642, 817, 657], "conf": 96.0}, {"text": "and", "bbox": [834, 637, 878, 657], "conf": 96.0}, {"text": "the", "bbox": [895, 637, 932, 657], "conf": 96.0}, {"text": "conference", "bbox": [949, 637, 1084, 657], "conf": 96.0}, {"text": "room", "bbox": [1102, 642, 1162, 657], "conf": 95.0}, {"text": "to", "bbox": [1178, 638, 1200, 657], "conf": 96.0}, {"text": "match", "bbox": [1218, 637, 1290, 657], "conf": 96.0}, {"text": "existing", "bbox": [1307, 637, 1399, 663], "conf": 96.0}, {"text": "tiles", "bbox": [1416, 637, 1464, 657], "conf": 95.0}, {"text": "in", "bbox": [1482, 637, 1500, 657], "conf": 95.0}, {"text": "Reception.", "bbox": [304, 668, 432, 694], "conf": 96.0}, {"text": "Landlord", "bbox": [303, 702, 408, 722], "conf": 95.0}, {"text": "is", "bbox": [419, 702, 436, 722], "conf": 95.0}, {"text": "not", "bbox": [447, 703, 484, 722], "conf": 96.0}, {"text": "responsible", "bbox": [493, 702, 632, 728], "conf": 95.0}, {"text": "for", "bbox": [641, 702, 674, 722], "conf": 96.0}, {"text": "any", "bbox": [682, 707, 726, 728], "conf": 93.0}, {"text": "IT/Phone", "bbox": [737, 702, 846, 722], "conf": 91.0}, {"text": "work.", "bbox": [855, 702, 918, 722], "conf": 95.0}, {"text": "Landlord", "bbox": [303, 736, 408, 756], "conf": 96.0}, {"text": "to", "bbox": [417, 737, 439, 756], "conf": 93.0}, {"text": "paint,carpet", "bbox": [449, 736, 592, 762], "conf": 92.0}, {"text": "and", "bbox": [600, 736, 644, 756], "conf": 96.0}, {"text": "Floor", "bbox": [650, 732, 706, 766], "conf": 96.0}, {"text": "tile", "bbox": [718, 736, 758, 756], "conf": 96.0}, {"text": "location", "bbox": [768, 736, 860, 756], "conf": 96.0}, {"text": "and", "bbox": [870, 736, 913, 756], "conf": 96.0}, {"text": "type", "bbox": [923, 737, 974, 762], "conf": 96.0}, {"text": "to", "bbox": [982, 737, 1004, 756], "conf": 96.0}, {"text": "by", "bbox": [1014, 736, 1041, 762], "conf": 96.0}, {"text": "determined.", "bbox": [1050, 736, 1193, 756], "conf": 96.0}, {"text": "the", "bbox": [1210, 736, 1247, 756], "conf": 96.0}, {"text": "Premises.", "bbox": [1258, 736, 1377, 756], "conf": 96.0}, {"text": "Landlord", "bbox": [1395, 736, 1500, 756], "conf": 96.0}, {"text": "and", "bbox": [302, 768, 346, 788], "conf": 97.0}, {"text": "Tenant", "bbox": [357, 768, 443, 788], "conf": 96.0}, {"text": "to", "bbox": [453, 769, 475, 788], "conf": 96.0}, {"text": "mutually", "bbox": [486, 768, 587, 794], "conf": 96.0}, {"text": "agree", "bbox": [598, 773, 667, 794], "conf": 96.0}, {"text": "on", "bbox": [678, 773, 706, 788], "conf": 93.0}, {"text": "color/design.", "bbox": [718, 768, 872, 794], "conf": 91.0}, {"text": "Landlord", "bbox": [894, 768, 999, 788], "conf": 96.0}, {"text": "will", "bbox": [1010, 768, 1046, 788], "conf": 96.0}, {"text": "provide", "bbox": [1059, 768, 1147, 794], "conf": 96.0}, {"text": "to", "bbox": [1157, 769, 1179, 788], "conf": 96.0}, {"text": "Tenant", "bbox": [1190, 768, 1276, 788], "conf": 96.0}, {"text": "two", "bbox": [1285, 769, 1327, 788], "conf": 96.0}, {"text": "hours", "bbox": [1339, 768, 1405, 788], "conf": 96.0}, {"text": "with", "bbox": [1416, 768, 1463, 788], "conf": 96.0}, {"text": "its", "bbox": [1476, 768, 1500, 788], "conf": 96.0}, {"text": "designer", "bbox": [302, 800, 408, 826], "conf": 96.0}, {"text": "to", "bbox": [416, 801, 438, 820], "conf": 96.0}, {"text": "pull", "bbox": [449, 800, 488, 826], "conf": 96.0}, {"text": "all", "bbox": [499, 800, 524, 820], "conf": 96.0}, {"text": "color", "bbox": [534, 800, 594, 820], "conf": 96.0}, {"text": "selections", "bbox": [602, 800, 724, 820], "conf": 96.0}, {"text": "together.", "bbox": [733, 800, 840, 826], "conf": 96.0}, {"text": "Landlord", "bbox": [303, 834, 408, 854], "conf": 96.0}, {"text": "to", "bbox": [421, 835, 443, 854], "conf": 96.0}, {"text": "replace", "bbox": [456, 834, 544, 860], "conf": 96.0}, {"text": "3", "bbox": [558, 834, 571, 854], "conf": 96.0}, {"text": "interior", "bbox": [584, 834, 668, 854], "conf": 96.0}, {"text": "doors", "bbox": [679, 834, 747, 854], "conf": 96.0}, {"text": "in", "bbox": [761, 834, 779, 854], "conf": 96.0}, {"text": "suite.", "bbox": [792, 834, 855, 854], "conf": 96.0}, {"text": "Landlord", "bbox": [870, 834, 975, 854], "conf": 96.0}, {"text": "will", "bbox": [988, 834, 1024, 854], "conf": 96.0}, {"text": "use", "bbox": [1038, 839, 1080, 854], "conf": 96.0}, {"text": "its", "bbox": [1094, 834, 1119, 854], "conf": 96.0}, {"text": "building", "bbox": [1133, 834, 1225, 860], "conf": 96.0}, {"text": "standard", "bbox": [1238, 834, 1344, 854], "conf": 96.0}, {"text": "(prefinished", "bbox": [1358, 834, 1500, 860], "conf": 96.0}, {"text": "Birch)", "bbox": [303, 866, 373, 892], "conf": 96.0}, {"text": "door", "bbox": [383, 866, 438, 886], "conf": 96.0}, {"text": "with", "bbox": [445, 866, 493, 886], "conf": 96.0}, {"text": "a", "bbox": [500, 862, 509, 896], "conf": 96.0}, {"text": "full", "bbox": [526, 866, 559, 886], "conf": 96.0}, {"text": "glass", "bbox": [570, 866, 632, 892], "conf": 96.0}, {"text": "insert", "bbox": [643, 866, 709, 886], "conf": 96.0}, {"text": "at", "bbox": [718, 867, 740, 886], "conf": 96.0}, {"text": "main", "bbox": [750, 866, 806, 886], "conf": 96.0}, {"text": "entry", "bbox": [817, 867, 877, 892], "conf": 96.0}, {"text": "only", "bbox": [886, 866, 936, 892], "conf": 96.0}, {"text": "so", "bbox": [945, 871, 972, 886], "conf": 97.0}, {"text": "that", "bbox": [981, 866, 1027, 886], "conf": 96.0}, {"text": "it", "bbox": [1037, 866, 1049, 886], "conf": 96.0}, {"text": "matches", "bbox": [1058, 866, 1160, 886], "conf": 96.0}, {"text": "corridor...", "bbox": [1170, 866, 1284, 886], "conf": 96.0}, {"text": "Landlord", "bbox": [303, 900, 408, 920], "conf": 96.0}, {"text": "to", "bbox": [419, 901, 441, 920], "conf": 96.0}, {"text": "match", "bbox": [452, 900, 524, 920], "conf": 96.0}, {"text": "(to", "bbox": [536, 900, 566, 926], "conf": 96.0}, {"text": "best", "bbox": [577, 900, 627, 920], "conf": 96.0}, {"text": "of", "bbox": [637, 900, 660, 920], "conf": 96.0}, {"text": "ability)", "bbox": [669, 900, 747, 926], "conf": 96.0}, {"text": "the", "bbox": [757, 900, 794, 920], "conf": 96.0}, {"text": "interior", "bbox": [806, 900, 889, 920], "conf": 96.0}, {"text": "doors", "bbox": [898, 900, 966, 920], "conf": 96.0}, {"text": "that", "bbox": [976, 900, 1022, 920], "conf": 96.0}, {"text": "are", "bbox": [1031, 905, 1069, 920], "conf": 96.0}, {"text": "in", "bbox": [1081, 900, 1099, 920], "conf": 96.0}, {"text": "Suite", "bbox": [1110, 900, 1171, 920], "conf": 96.0}, {"text": "135.", "bbox": [1184, 900, 1233, 920], "conf": 96.0}, {"text": "All", "bbox": [1252, 900, 1281, 920], "conf": 96.0}, {"text": "interior", "bbox": [1293, 900, 1377, 920], "conf": 96.0}, {"text": "doors", "bbox": [1386, 900, 1453, 920], "conf": 96.0}, {"text": "will", "bbox": [1463, 900, 1500, 920], "conf": 95.0}, {"text": "match", "bbox": [303, 932, 375, 952], "conf": 96.0}, {"text": "throughout", "bbox": [385, 932, 517, 958], "conf": 96.0}, {"text": "the", "bbox": [526, 932, 563, 952], "conf": 96.0}, {"text": "space", "bbox": [573, 937, 645, 958], "conf": 96.0}, {"text": "and", "bbox": [654, 932, 698, 952], "conf": 96.0}, {"text": "will", "bbox": [708, 932, 744, 952], "conf": 96.0}, {"text": "have", "bbox": [756, 932, 813, 952], "conf": 96.0}, {"text": "full-length", "bbox": [822, 932, 940, 958], "conf": 96.0}, {"text": "light", "bbox": [952, 932, 1001, 958], "conf": 96.0}, {"text": "kits", "bbox": [1011, 932, 1049, 952], "conf": 96.0}, {"text": "installed.", "bbox": [1060, 932, 1165, 952], "conf": 95.0}, {"text": "Landlord", "bbox": [303, 966, 408, 986], "conf": 96.0}, {"text": "to", "bbox": [418, 967, 440, 986], "conf": 96.0}, {"text": "construct", "bbox": [449, 967, 561, 986], "conf": 96.0}, {"text": "devising", "bbox": [570, 966, 669, 992], "conf": 96.0}, {"text": "walls", "bbox": [679, 966, 739, 986], "conf": 96.0}, {"text": "between", "bbox": [750, 966, 851, 986], "conf": 96.0}, {"text": "201", "bbox": [861, 966, 902, 986], "conf": 93.0}, {"text": "(Tenant))", "bbox": [916, 966, 1028, 992], "conf": 93.0}, {"text": "and", "bbox": [1037, 966, 1081, 986], "conf": 96.0}, {"text": "Suite", "bbox": [1092, 966, 1153, 986], "conf": 96.0}, {"text": "200", "bbox": [1162, 966, 1207, 986], "conf": 96.0}, {"text": "(available", "bbox": [1217, 966, 1333, 992], "conf": 96.0}, {"text": "for", "bbox": [1342, 966, 1375, 986], "conf": 96.0}, {"text": "Lease)", "bbox": [1384, 966, 1466, 992], "conf": 96.0}, {"text": "Landlord", "bbox": [303, 999, 408, 1019], "conf": 96.0}, {"text": "to", "bbox": [418, 1000, 440, 1019], "conf": 96.0}, {"text": "modify", "bbox": [450, 999, 530, 1025], "conf": 96.0}, {"text": "area", "bbox": [539, 1004, 592, 1019], "conf": 96.0}, {"text": "where", "bbox": [601, 999, 676, 1019], "conf": 95.0}, {"text": "two", "bbox": [685, 1000, 727, 1019], "conf": 95.0}, {"text": "offices", "bbox": [736, 999, 815, 1019], "conf": 95.0}, {"text": "become", "bbox": [825, 999, 921, 1019], "conf": 96.0}, {"text": "a", "bbox": [931, 1004, 944, 1019], "conf": 96.0}, {"text": "conference", "bbox": [954, 999, 1089, 1019], "conf": 96.0}, {"text": "room,", "bbox": [1100, 1004, 1167, 1023], "conf": 96.0}, {"text": "at", "bbox": [1178, 1000, 1200, 1019], "conf": 96.0}, {"text": "its", "bbox": [1210, 999, 1235, 1019], "conf": 96.0}, {"text": "sole", "bbox": [1245, 999, 1293, 1019], "conf": 96.0}, {"text": "cost.", "bbox": [1303, 1000, 1358, 1019], "conf": 95.0}, {"text": "Landlord", "bbox": [303, 1033, 408, 1053], "conf": 96.0}, {"text": "to", "bbox": [418, 1034, 440, 1053], "conf": 96.0}, {"text": "update", "bbox": [450, 1033, 532, 1059], "conf": 96.0}, {"text": "ceiling", "bbox": [542, 1033, 618, 1059], "conf": 96.0}, {"text": "tiles", "bbox": [628, 1033, 676, 1053], "conf": 96.0}, {"text": "in", "bbox": [686, 1033, 704, 1053], "conf": 96.0}, {"text": "common", "bbox": [715, 1038, 819, 1053], "conf": 96.0}, {"text": "areas,", "bbox": [829, 1038, 903, 1057], "conf": 96.0}, {"text": "open", "bbox": [914, 1038, 973, 1059], "conf": 96.0}, {"text": "workspace", "bbox": [983, 1033, 1114, 1059], "conf": 96.0}, {"text": "and", "bbox": [1124, 1033, 1168, 1053], "conf": 96.0}, {"text": "conference", "bbox": [1178, 1033, 1313, 1053], "conf": 95.0}, {"text": "room.", "bbox": [1324, 1038, 1391, 1053], "conf": 96.0}, {"text": "Landlord", "bbox": [303, 1067, 408, 1087], "conf": 96.0}, {"text": "to", "bbox": [419, 1068, 441, 1087], "conf": 96.0}, {"text": "ensure", "bbox": [451, 1072, 534, 1087], "conf": 96.0}, {"text": "the", "bbox": [545, 1067, 582, 1087], "conf": 96.0}, {"text": "Premises", "bbox": [594, 1067, 707, 1087], "conf": 96.0}, {"text": "is", "bbox": [718, 1067, 736, 1087], "conf": 96.0}, {"text": "professionally", "bbox": [747, 1067, 915, 1093], "conf": 96.0}, {"text": "cleaned", "bbox": [925, 1067, 1020, 1087], "conf": 96.0}, {"text": "prior", "bbox": [1032, 1067, 1086, 1093], "conf": 96.0}, {"text": "to", "bbox": [1095, 1068, 1117, 1087], "conf": 93.0}, {"text": "Tenant\u2019s", "bbox": [1128, 1067, 1233, 1087], "conf": 90.0}, {"text": "occupancy,", "bbox": [1243, 1072, 1381, 1093], "conf": 96.0}, {"text": "including", "bbox": [1394, 1067, 1500, 1093], "conf": 96.0}, {"text": "but", "bbox": [303, 1099, 340, 1119], "conf": 96.0}, {"text": "not", "bbox": [350, 1100, 386, 1119], "conf": 96.0}, {"text": "limited", "bbox": [396, 1099, 473, 1119], "conf": 96.0}, {"text": "to", "bbox": [483, 1100, 505, 1119], "conf": 96.0}, {"text": "existing", "bbox": [514, 1099, 606, 1125], "conf": 96.0}, {"text": "cabinets,", "bbox": [616, 1099, 724, 1123], "conf": 96.0}, {"text": "kitchen,", "bbox": [736, 1099, 827, 1123], "conf": 96.0}, {"text": "and", "bbox": [838, 1099, 882, 1119], "conf": 96.0}, {"text": "any", "bbox": [892, 1104, 936, 1125], "conf": 96.0}, {"text": "necessary", "bbox": [946, 1104, 1070, 1125], "conf": 96.0}, {"text": "pest", "bbox": [1080, 1100, 1131, 1125], "conf": 96.0}, {"text": "prevention.", "bbox": [1140, 1099, 1274, 1125], "conf": 96.0}, {"text": "A", "bbox": [1046, 2595, 1070, 2617], "conf": 95.0}, {"text": "Glimmer", "bbox": [1080, 2594, 1208, 2618], "conf": 95.0}, {"text": "of", "bbox": [1217, 2594, 1247, 2617], "conf": 96.0}, {"text": "Hope", "bbox": [1253, 2595, 1327, 2624], "conf": 96.0}, {"text": "Foundation", "bbox": [1337, 2594, 1500, 2617], "conf": 96.0}, {"text": "January", "bbox": [1275, 2633, 1392, 2662], "conf": 96.0}, {"text": "1,", "bbox": [1404, 2633, 1426, 2661], "conf": 95.0}, {"text": "2022", "bbox": [1436, 2632, 1500, 2655], "conf": 95.0}]}