{"engine": "tesseract", "page": 30, "words": [{"text": "which,", "bbox": [302, 208, 358, 228], "conf": 96.0}, {"text": "in", "bbox": [386, 210, 408, 228], "conf": 93.0}, {"text": "Landlord\u2019s", "bbox": [416, 208, 540, 228], "conf": 92.0}, {"text": "judgment,", "bbox": [547, 208, 665, 234], "conf": 96.0}, {"text": "is", "bbox": [673, 210, 691, 228], "conf": 96.0}, {"text": "inconsistent", "bbox": [699, 210, 843, 228], "conf": 96.0}, {"text": "with", "bbox": [850, 208, 902, 228], "conf": 96.0}, {"text": "the", "bbox": [911, 208, 947, 228], "conf": 96.0}, {"text": "quality", "bbox": [955, 208, 1037, 234], "conf": 96.0}, {"text": "of", "bbox": [1046, 208, 1068, 228], "conf": 96.0}, {"text": "operations", "bbox": [1073, 208, 1199, 234], "conf": 96.0}, {"text": "of", "bbox": [1207, 208, 1231, 228], "conf": 96.0}, {"text": "the", "bbox": [1237, 208, 1273, 228], "conf": 96.0}, {"text": "Property", "bbox": [1282, 209, 1386, 234], "conf": 96.0}, {"text": "or", "bbox": [1393, 215, 1418, 228], "conf": 96.0}, {"text": "may", "bbox": [1425, 215, 1475, 234], "conf": 96.0}, {"text": "tend", "bbox": [302, 240, 355, 260], "conf": 96.0}, {"text": "to", "bbox": [362, 243, 384, 260], "conf": 96.0}, {"text": "impose", "bbox": [392, 242, 477, 266], "conf": 96.0}, {"text": "or", "bbox": [485, 247, 510, 260], "conf": 97.0}, {"text": "detract", "bbox": [517, 240, 601, 260], "conf": 96.0}, {"text": "from", "bbox": [609, 240, 664, 260], "conf": 96.0}, {"text": "the", "bbox": [673, 240, 709, 260], "conf": 96.0}, {"text": "moral", "bbox": [717, 240, 785, 260], "conf": 96.0}, {"text": "character", "bbox": [794, 240, 905, 260], "conf": 96.0}, {"text": "or", "bbox": [913, 247, 937, 260], "conf": 96.0}, {"text": "image", "bbox": [945, 242, 1015, 266], "conf": 96.0}, {"text": "of", "bbox": [1017, 236, 1035, 270], "conf": 96.0}, {"text": "the", "bbox": [1038, 240, 1089, 260], "conf": 96.0}, {"text": "Property.", "bbox": [1097, 241, 1205, 266], "conf": 96.0}, {"text": "3.", "bbox": [303, 297, 321, 316], "conf": 96.0}, {"text": "Landlord", "bbox": [330, 296, 436, 316], "conf": 96.0}, {"text": "shall", "bbox": [444, 296, 497, 316], "conf": 96.0}, {"text": "have", "bbox": [506, 296, 561, 316], "conf": 96.0}, {"text": "the", "bbox": [569, 296, 605, 316], "conf": 96.0}, {"text": "right", "bbox": [613, 296, 669, 322], "conf": 96.0}, {"text": "to", "bbox": [677, 299, 698, 316], "conf": 96.0}, {"text": "prescribe", "bbox": [707, 296, 818, 322], "conf": 96.0}, {"text": "the", "bbox": [826, 296, 862, 316], "conf": 97.0}, {"text": "weight", "bbox": [870, 296, 950, 322], "conf": 96.0}, {"text": "and", "bbox": [957, 296, 1000, 316], "conf": 97.0}, {"text": "position", "bbox": [1008, 298, 1104, 322], "conf": 96.0}, {"text": "of", "bbox": [1106, 292, 1123, 326], "conf": 96.0}, {"text": "file", "bbox": [1126, 296, 1176, 316], "conf": 96.0}, {"text": "systems,", "bbox": [1184, 299, 1283, 322], "conf": 96.0}, {"text": "safes,", "bbox": [1291, 296, 1354, 319], "conf": 96.0}, {"text": "computer", "bbox": [1363, 299, 1477, 322], "conf": 96.0}, {"text": "systems,", "bbox": [302, 331, 401, 354], "conf": 96.0}, {"text": "and", "bbox": [410, 328, 453, 348], "conf": 96.0}, {"text": "other", "bbox": [460, 328, 523, 348], "conf": 96.0}, {"text": "heavy", "bbox": [531, 328, 600, 354], "conf": 96.0}, {"text": "items,", "bbox": [608, 330, 676, 351], "conf": 96.0}, {"text": "equipment", "bbox": [685, 330, 813, 354], "conf": 96.0}, {"text": "and", "bbox": [820, 328, 863, 348], "conf": 96.0}, {"text": "fixtures,", "bbox": [871, 328, 965, 351], "conf": 96.0}, {"text": "which", "bbox": [974, 328, 1044, 348], "conf": 96.0}, {"text": "shall,", "bbox": [1052, 328, 1111, 351], "conf": 95.0}, {"text": "if", "bbox": [1120, 328, 1136, 348], "conf": 96.0}, {"text": "considered", "bbox": [1142, 328, 1272, 348], "conf": 96.0}, {"text": "necessary", "bbox": [1280, 335, 1396, 354], "conf": 96.0}, {"text": "by", "bbox": [1404, 328, 1432, 354], "conf": 97.0}, {"text": "Landlord,", "bbox": [303, 360, 414, 383], "conf": 96.0}, {"text": "be", "bbox": [422, 360, 450, 380], "conf": 97.0}, {"text": "positioned", "bbox": [457, 360, 582, 386], "conf": 96.0}, {"text": "in", "bbox": [590, 362, 611, 380], "conf": 97.0}, {"text": "consultation", "bbox": [619, 360, 765, 380], "conf": 96.0}, {"text": "with", "bbox": [773, 360, 824, 380], "conf": 96.0}, {"text": "Landlord", "bbox": [834, 360, 940, 380], "conf": 96.0}, {"text": "in", "bbox": [947, 362, 969, 380], "conf": 96.0}, {"text": "order", "bbox": [977, 360, 1042, 380], "conf": 96.0}, {"text": "to", "bbox": [1050, 363, 1071, 380], "conf": 96.0}, {"text": "distribute", "bbox": [1080, 360, 1195, 380], "conf": 96.0}, {"text": "their", "bbox": [1203, 360, 1259, 380], "conf": 96.0}, {"text": "weight.", "bbox": [1267, 360, 1351, 386], "conf": 96.0}, {"text": "Any", "bbox": [1359, 361, 1406, 386], "conf": 96.0}, {"text": "and", "bbox": [1413, 360, 1456, 380], "conf": 96.0}, {"text": "all", "bbox": [1463, 360, 1489, 380], "conf": 96.0}, {"text": "damage", "bbox": [302, 393, 393, 419], "conf": 96.0}, {"text": "or", "bbox": [401, 400, 426, 413], "conf": 96.0}, {"text": "injury", "bbox": [433, 395, 504, 419], "conf": 96.0}, {"text": "to", "bbox": [511, 396, 532, 413], "conf": 96.0}, {"text": "the", "bbox": [541, 393, 578, 413], "conf": 96.0}, {"text": "Premises", "bbox": [587, 394, 693, 413], "conf": 96.0}, {"text": "or", "bbox": [701, 400, 726, 413], "conf": 96.0}, {"text": "the", "bbox": [733, 393, 770, 413], "conf": 96.0}, {"text": "Building", "bbox": [779, 393, 877, 419], "conf": 96.0}, {"text": "caused", "bbox": [884, 393, 964, 413], "conf": 96.0}, {"text": "by", "bbox": [972, 393, 1000, 419], "conf": 96.0}, {"text": "moving", "bbox": [1007, 395, 1095, 419], "conf": 96.0}, {"text": "the", "bbox": [1102, 393, 1139, 413], "conf": 96.0}, {"text": "property", "bbox": [1146, 396, 1251, 419], "conf": 96.0}, {"text": "of", "bbox": [1258, 393, 1282, 413], "conf": 96.0}, {"text": "Tenant", "bbox": [1287, 393, 1370, 413], "conf": 96.0}, {"text": "into", "bbox": [1378, 395, 1422, 413], "conf": 96.0}, {"text": "or", "bbox": [1431, 400, 1456, 413], "conf": 96.0}, {"text": "out", "bbox": [302, 429, 340, 446], "conf": 96.0}, {"text": "of", "bbox": [348, 433, 360, 446], "conf": 96.0}, {"text": "the", "bbox": [377, 426, 414, 446], "conf": 96.0}, {"text": "Building,", "bbox": [422, 426, 524, 452], "conf": 96.0}, {"text": "or", "bbox": [533, 433, 558, 446], "conf": 96.0}, {"text": "due", "bbox": [565, 426, 608, 446], "conf": 96.0}, {"text": "to", "bbox": [616, 429, 637, 446], "conf": 96.0}, {"text": "the", "bbox": [646, 426, 683, 446], "conf": 96.0}, {"text": "same", "bbox": [690, 433, 751, 446], "conf": 96.0}, {"text": "being", "bbox": [759, 426, 824, 452], "conf": 96.0}, {"text": "in", "bbox": [831, 428, 852, 446], "conf": 96.0}, {"text": "or", "bbox": [860, 433, 885, 446], "conf": 96.0}, {"text": "upon", "bbox": [892, 433, 952, 446], "conf": 96.0}, {"text": "the", "bbox": [959, 426, 996, 446], "conf": 95.0}, {"text": "Premises,", "bbox": [1005, 427, 1116, 449], "conf": 95.0}, {"text": "shall", "bbox": [1125, 426, 1178, 446], "conf": 97.0}, {"text": "be", "bbox": [1187, 426, 1214, 446], "conf": 97.0}, {"text": "repaired", "bbox": [1222, 426, 1322, 452], "conf": 96.0}, {"text": "by", "bbox": [1330, 426, 1358, 452], "conf": 97.0}, {"text": "and", "bbox": [1365, 426, 1408, 446], "conf": 96.0}, {"text": "at", "bbox": [1416, 429, 1437, 446], "conf": 96.0}, {"text": "the", "bbox": [1445, 426, 1482, 446], "conf": 96.0}, {"text": "sole", "bbox": [302, 458, 348, 478], "conf": 96.0}, {"text": "cost", "bbox": [356, 461, 403, 478], "conf": 96.0}, {"text": "of", "bbox": [410, 458, 434, 478], "conf": 97.0}, {"text": "Tenant.", "bbox": [440, 459, 527, 478], "conf": 96.0}, {"text": "No", "bbox": [536, 459, 566, 478], "conf": 96.0}, {"text": "furniture,", "bbox": [575, 458, 686, 481], "conf": 96.0}, {"text": "equipment", "bbox": [695, 460, 823, 484], "conf": 95.0}, {"text": "or", "bbox": [830, 465, 855, 478], "conf": 95.0}, {"text": "other", "bbox": [862, 458, 926, 478], "conf": 96.0}, {"text": "bulky", "bbox": [933, 458, 999, 484], "conf": 96.0}, {"text": "matter", "bbox": [1006, 461, 1085, 478], "conf": 96.0}, {"text": "of", "bbox": [1093, 458, 1116, 478], "conf": 96.0}, {"text": "any", "bbox": [1122, 465, 1164, 484], "conf": 96.0}, {"text": "description", "bbox": [1171, 458, 1305, 484], "conf": 96.0}, {"text": "will", "bbox": [1312, 458, 1354, 478], "conf": 96.0}, {"text": "be", "bbox": [1363, 458, 1390, 478], "conf": 96.0}, {"text": "received", "bbox": [1397, 458, 1498, 478], "conf": 96.0}, {"text": "into", "bbox": [302, 493, 347, 511], "conf": 96.0}, {"text": "the", "bbox": [356, 494, 392, 511], "conf": 96.0}, {"text": "Building", "bbox": [401, 491, 499, 517], "conf": 96.0}, {"text": "or", "bbox": [506, 498, 531, 511], "conf": 96.0}, {"text": "carried", "bbox": [538, 491, 622, 511], "conf": 96.0}, {"text": "in", "bbox": [630, 493, 652, 511], "conf": 96.0}, {"text": "the", "bbox": [659, 491, 696, 511], "conf": 96.0}, {"text": "elevators", "bbox": [704, 491, 812, 511], "conf": 96.0}, {"text": "(if", "bbox": [821, 491, 847, 517], "conf": 95.0}, {"text": "any)", "bbox": [852, 491, 902, 517], "conf": 95.0}, {"text": "except", "bbox": [912, 494, 988, 517], "conf": 96.0}, {"text": "as", "bbox": [996, 498, 1019, 511], "conf": 96.0}, {"text": "approved", "bbox": [1028, 491, 1140, 517], "conf": 95.0}, {"text": "by", "bbox": [1147, 491, 1175, 517], "conf": 95.0}, {"text": "Landlord", "bbox": [1184, 491, 1290, 511], "conf": 96.0}, {"text": "and", "bbox": [1297, 491, 1340, 511], "conf": 96.0}, {"text": "all", "bbox": [1348, 491, 1374, 511], "conf": 96.0}, {"text": "such", "bbox": [1383, 491, 1435, 511], "conf": 96.0}, {"text": "furniture,", "bbox": [302, 524, 413, 547], "conf": 96.0}, {"text": "equipment", "bbox": [422, 526, 550, 550], "conf": 96.0}, {"text": "and", "bbox": [557, 524, 600, 544], "conf": 96.0}, {"text": "other", "bbox": [608, 524, 671, 544], "conf": 96.0}, {"text": "bulky", "bbox": [678, 524, 744, 550], "conf": 96.0}, {"text": "matter", "bbox": [751, 527, 830, 544], "conf": 96.0}, {"text": "shall", "bbox": [838, 524, 891, 544], "conf": 96.0}, {"text": "be", "bbox": [900, 524, 927, 544], "conf": 96.0}, {"text": "delivered", "bbox": [935, 524, 1045, 544], "conf": 96.0}, {"text": "only", "bbox": [1053, 524, 1104, 550], "conf": 96.0}, {"text": "through", "bbox": [1111, 524, 1204, 550], "conf": 96.0}, {"text": "the", "bbox": [1212, 524, 1249, 544], "conf": 96.0}, {"text": "designated", "bbox": [1257, 524, 1385, 550], "conf": 96.0}, {"text": "delivery", "bbox": [1393, 524, 1489, 550], "conf": 96.0}, {"text": "entrance", "bbox": [302, 559, 405, 576], "conf": 96.0}, {"text": "of", "bbox": [408, 552, 425, 586], "conf": 96.0}, {"text": "the", "bbox": [428, 556, 479, 576], "conf": 96.0}, {"text": "Building.", "bbox": [488, 556, 590, 582], "conf": 96.0}, {"text": "All", "bbox": [604, 556, 634, 576], "conf": 96.0}, {"text": "moving", "bbox": [643, 558, 731, 582], "conf": 96.0}, {"text": "of", "bbox": [738, 552, 757, 586], "conf": 96.0}, {"text": "furniture,", "bbox": [753, 556, 879, 579], "conf": 96.0}, {"text": "equipment", "bbox": [887, 558, 1015, 582], "conf": 96.0}, {"text": "and", "bbox": [1022, 556, 1065, 576], "conf": 96.0}, {"text": "other", "bbox": [1073, 556, 1136, 576], "conf": 96.0}, {"text": "materials", "bbox": [1144, 556, 1253, 576], "conf": 96.0}, {"text": "shall", "bbox": [1261, 556, 1315, 576], "conf": 96.0}, {"text": "be", "bbox": [1323, 556, 1351, 576], "conf": 96.0}, {"text": "under", "bbox": [1358, 556, 1428, 576], "conf": 96.0}, {"text": "the", "bbox": [1436, 556, 1472, 576], "conf": 96.0}, {"text": "direct", "bbox": [302, 588, 371, 608], "conf": 96.0}, {"text": "control", "bbox": [378, 588, 461, 608], "conf": 96.0}, {"text": "and", "bbox": [470, 588, 513, 608], "conf": 96.0}, {"text": "supervision", "bbox": [520, 590, 658, 614], "conf": 96.0}, {"text": "of", "bbox": [666, 588, 690, 608], "conf": 96.0}, {"text": "Landlord", "bbox": [696, 588, 802, 608], "conf": 96.0}, {"text": "who", "bbox": [810, 588, 859, 608], "conf": 96.0}, {"text": "shall", "bbox": [867, 588, 921, 608], "conf": 96.0}, {"text": "not,", "bbox": [929, 591, 972, 611], "conf": 96.0}, {"text": "however,", "bbox": [981, 588, 1088, 611], "conf": 96.0}, {"text": "be", "bbox": [1097, 588, 1124, 608], "conf": 97.0}, {"text": "responsible", "bbox": [1132, 588, 1269, 614], "conf": 96.0}, {"text": "for", "bbox": [1276, 588, 1310, 608], "conf": 96.0}, {"text": "any", "bbox": [1317, 595, 1359, 614], "conf": 96.0}, {"text": "damage", "bbox": [1366, 588, 1458, 614], "conf": 96.0}, {"text": "to", "bbox": [1465, 591, 1487, 608], "conf": 96.0}, {"text": "or", "bbox": [302, 628, 327, 641], "conf": 96.0}, {"text": "charges", "bbox": [334, 621, 424, 647], "conf": 96.0}, {"text": "for", "bbox": [432, 621, 466, 641], "conf": 96.0}, {"text": "moving", "bbox": [473, 623, 561, 647], "conf": 96.0}, {"text": "the", "bbox": [568, 621, 605, 641], "conf": 96.0}, {"text": "same.", "bbox": [613, 628, 678, 641], "conf": 96.0}, {"text": "Tenant", "bbox": [693, 622, 775, 641], "conf": 96.0}, {"text": "agrees", "bbox": [783, 628, 859, 647], "conf": 95.0}, {"text": "promptly", "bbox": [867, 621, 977, 647], "conf": 96.0}, {"text": "to", "bbox": [984, 624, 1005, 641], "conf": 96.0}, {"text": "remove", "bbox": [1014, 628, 1103, 641], "conf": 96.0}, {"text": "from", "bbox": [1111, 621, 1166, 641], "conf": 96.0}, {"text": "the", "bbox": [1175, 621, 1211, 641], "conf": 96.0}, {"text": "sidewalks", "bbox": [1219, 621, 1335, 641], "conf": 96.0}, {"text": "adjacent", "bbox": [1343, 621, 1442, 647], "conf": 96.0}, {"text": "to", "bbox": [1450, 624, 1471, 641], "conf": 96.0}, {"text": "the", "bbox": [302, 654, 339, 674], "conf": 96.0}, {"text": "Building", "bbox": [348, 654, 446, 680], "conf": 96.0}, {"text": "any", "bbox": [453, 661, 495, 680], "conf": 96.0}, {"text": "of", "bbox": [502, 654, 525, 674], "conf": 93.0}, {"text": "Tenant\u2019s", "bbox": [531, 654, 631, 674], "conf": 70.0}, {"text": "furniture,", "bbox": [639, 654, 750, 677], "conf": 96.0}, {"text": "equipment", "bbox": [759, 656, 887, 680], "conf": 96.0}, {"text": "or", "bbox": [894, 661, 919, 674], "conf": 96.0}, {"text": "other", "bbox": [927, 654, 990, 674], "conf": 96.0}, {"text": "materials", "bbox": [997, 654, 1107, 674], "conf": 96.0}, {"text": "delivered", "bbox": [1115, 654, 1226, 674], "conf": 96.0}, {"text": "or", "bbox": [1233, 661, 1258, 674], "conf": 96.0}, {"text": "deposited.", "bbox": [1266, 654, 1386, 680], "conf": 96.0}, {"text": "4.", "bbox": [302, 720, 321, 739], "conf": 94.0}, {"text": "No", "bbox": [330, 720, 360, 739], "conf": 94.0}, {"text": "additional", "bbox": [369, 719, 487, 739], "conf": 95.0}, {"text": "locks", "bbox": [496, 719, 555, 739], "conf": 96.0}, {"text": "or", "bbox": [563, 726, 588, 739], "conf": 96.0}, {"text": "bolts", "bbox": [595, 719, 652, 739], "conf": 96.0}, {"text": "of", "bbox": [660, 719, 684, 739], "conf": 96.0}, {"text": "any", "bbox": [689, 726, 731, 745], "conf": 96.0}, {"text": "kind", "bbox": [739, 719, 790, 739], "conf": 96.0}, {"text": "shall", "bbox": [798, 719, 851, 739], "conf": 96.0}, {"text": "be", "bbox": [860, 719, 887, 739], "conf": 96.0}, {"text": "placed", "bbox": [895, 719, 971, 745], "conf": 96.0}, {"text": "upon", "bbox": [979, 726, 1038, 745], "conf": 96.0}, {"text": "any", "bbox": [1046, 726, 1088, 745], "conf": 96.0}, {"text": "of", "bbox": [1088, 715, 1107, 749], "conf": 96.0}, {"text": "the", "bbox": [1110, 719, 1161, 739], "conf": 96.0}, {"text": "doors", "bbox": [1169, 719, 1235, 739], "conf": 96.0}, {"text": "or", "bbox": [1243, 726, 1268, 739], "conf": 96.0}, {"text": "windows", "bbox": [1275, 719, 1382, 739], "conf": 96.0}, {"text": "by", "bbox": [1390, 719, 1418, 745], "conf": 96.0}, {"text": "Tenant,", "bbox": [302, 753, 389, 775], "conf": 96.0}, {"text": "nor", "bbox": [398, 759, 438, 772], "conf": 96.0}, {"text": "shall", "bbox": [446, 752, 499, 772], "conf": 96.0}, {"text": "any", "bbox": [508, 759, 550, 778], "conf": 96.0}, {"text": "changes", "bbox": [557, 752, 651, 778], "conf": 96.0}, {"text": "be", "bbox": [659, 752, 686, 772], "conf": 97.0}, {"text": "made", "bbox": [694, 752, 758, 772], "conf": 95.0}, {"text": "in", "bbox": [765, 754, 787, 772], "conf": 95.0}, {"text": "existing", "bbox": [795, 754, 887, 778], "conf": 96.0}, {"text": "locks", "bbox": [894, 752, 953, 772], "conf": 96.0}, {"text": "or", "bbox": [961, 759, 986, 772], "conf": 97.0}, {"text": "the", "bbox": [993, 752, 1030, 772], "conf": 96.0}, {"text": "mechanism", "bbox": [1038, 752, 1172, 772], "conf": 96.0}, {"text": "thereof.", "bbox": [1180, 752, 1269, 772], "conf": 96.0}, {"text": "Tenant", "bbox": [1281, 753, 1363, 772], "conf": 96.0}, {"text": "shall,", "bbox": [1371, 752, 1430, 775], "conf": 96.0}, {"text": "upon", "bbox": [1439, 759, 1498, 778], "conf": 96.0}, {"text": "the", "bbox": [302, 784, 339, 804], "conf": 96.0}, {"text": "expiration", "bbox": [347, 786, 468, 810], "conf": 96.0}, {"text": "or", "bbox": [475, 791, 500, 804], "conf": 96.0}, {"text": "termination", "bbox": [508, 786, 648, 804], "conf": 96.0}, {"text": "of", "bbox": [655, 784, 679, 804], "conf": 95.0}, {"text": "its", "bbox": [685, 786, 712, 804], "conf": 95.0}, {"text": "tenancy,", "bbox": [720, 787, 817, 810], "conf": 96.0}, {"text": "return", "bbox": [826, 787, 901, 804], "conf": 96.0}, {"text": "to", "bbox": [908, 787, 930, 804], "conf": 96.0}, {"text": "Landlord", "bbox": [940, 784, 1046, 804], "conf": 96.0}, {"text": "all", "bbox": [1053, 784, 1080, 804], "conf": 96.0}, {"text": "keys", "bbox": [1088, 784, 1140, 810], "conf": 97.0}, {"text": "used", "bbox": [1148, 784, 1203, 804], "conf": 96.0}, {"text": "in", "bbox": [1211, 786, 1233, 804], "conf": 96.0}, {"text": "connection", "bbox": [1240, 786, 1370, 804], "conf": 96.0}, {"text": "with", "bbox": [1377, 784, 1429, 804], "conf": 97.0}, {"text": "the", "bbox": [1438, 784, 1474, 804], "conf": 96.0}, {"text": "Premises,", "bbox": [303, 817, 414, 839], "conf": 96.0}, {"text": "including", "bbox": [423, 816, 533, 842], "conf": 96.0}, {"text": "any", "bbox": [540, 823, 582, 842], "conf": 96.0}, {"text": "keys", "bbox": [589, 816, 641, 842], "conf": 96.0}, {"text": "to", "bbox": [649, 819, 671, 836], "conf": 96.0}, {"text": "the", "bbox": [679, 816, 716, 836], "conf": 96.0}, {"text": "Premises,", "bbox": [725, 817, 836, 839], "conf": 96.0}, {"text": "to", "bbox": [845, 819, 866, 836], "conf": 96.0}, {"text": "rooms", "bbox": [875, 823, 949, 836], "conf": 96.0}, {"text": "and", "bbox": [957, 816, 1000, 836], "conf": 96.0}, {"text": "offices", "bbox": [1008, 816, 1083, 836], "conf": 96.0}, {"text": "within", "bbox": [1091, 816, 1167, 836], "conf": 96.0}, {"text": "the", "bbox": [1174, 816, 1211, 836], "conf": 96.0}, {"text": "Premises,", "bbox": [1220, 817, 1331, 839], "conf": 96.0}, {"text": "to", "bbox": [1339, 819, 1361, 836], "conf": 97.0}, {"text": "storage", "bbox": [1370, 819, 1457, 842], "conf": 96.0}, {"text": "rooms", "bbox": [302, 856, 376, 869], "conf": 95.0}, {"text": "and", "bbox": [384, 849, 427, 869], "conf": 95.0}, {"text": "closets,", "bbox": [435, 849, 519, 872], "conf": 95.0}, {"text": "to", "bbox": [528, 852, 549, 869], "conf": 96.0}, {"text": "cabinets", "bbox": [558, 849, 655, 869], "conf": 96.0}, {"text": "and", "bbox": [663, 849, 706, 869], "conf": 96.0}, {"text": "other", "bbox": [714, 849, 777, 869], "conf": 96.0}, {"text": "built-in", "bbox": [785, 849, 871, 869], "conf": 96.0}, {"text": "furniture,", "bbox": [878, 849, 990, 872], "conf": 96.0}, {"text": "mailbox,", "bbox": [999, 849, 1097, 872], "conf": 96.0}, {"text": "and", "bbox": [1106, 849, 1149, 869], "conf": 96.0}, {"text": "to", "bbox": [1156, 852, 1178, 869], "conf": 96.0}, {"text": "toilet", "bbox": [1187, 849, 1248, 869], "conf": 96.0}, {"text": "rooms,", "bbox": [1255, 856, 1334, 872], "conf": 95.0}, {"text": "whether", "bbox": [1343, 849, 1442, 869], "conf": 96.0}, {"text": "such", "bbox": [302, 882, 355, 902], "conf": 96.0}, {"text": "keys", "bbox": [363, 882, 415, 908], "conf": 96.0}, {"text": "were", "bbox": [423, 889, 482, 902], "conf": 96.0}, {"text": "furnished", "bbox": [490, 882, 603, 902], "conf": 96.0}, {"text": "by", "bbox": [610, 882, 639, 908], "conf": 96.0}, {"text": "Landlord", "bbox": [647, 882, 753, 902], "conf": 96.0}, {"text": "or", "bbox": [760, 889, 785, 902], "conf": 96.0}, {"text": "procured", "bbox": [793, 882, 901, 908], "conf": 96.0}, {"text": "by", "bbox": [908, 882, 937, 908], "conf": 96.0}, {"text": "Tenant", "bbox": [944, 883, 1026, 902], "conf": 96.0}, {"text": "and", "bbox": [1034, 882, 1077, 902], "conf": 96.0}, {"text": "in", "bbox": [1084, 884, 1106, 902], "conf": 96.0}, {"text": "the", "bbox": [1114, 882, 1150, 902], "conf": 96.0}, {"text": "event", "bbox": [1158, 885, 1223, 902], "conf": 96.0}, {"text": "of", "bbox": [1230, 882, 1254, 902], "conf": 96.0}, {"text": "the", "bbox": [1260, 882, 1296, 902], "conf": 96.0}, {"text": "loss", "bbox": [1304, 882, 1348, 902], "conf": 96.0}, {"text": "of", "bbox": [1357, 882, 1380, 902], "conf": 96.0}, {"text": "any", "bbox": [1385, 889, 1427, 908], "conf": 96.0}, {"text": "such", "bbox": [1435, 882, 1487, 902], "conf": 96.0}, {"text": "keys,", "bbox": [302, 914, 359, 940], "conf": 96.0}, {"text": "Tenant", "bbox": [368, 915, 451, 934], "conf": 96.0}, {"text": "shall", "bbox": [458, 914, 511, 934], "conf": 96.0}, {"text": "pay", "bbox": [520, 921, 562, 940], "conf": 96.0}, {"text": "to", "bbox": [569, 917, 591, 934], "conf": 97.0}, {"text": "Landlord", "bbox": [600, 914, 707, 934], "conf": 96.0}, {"text": "the", "bbox": [714, 914, 751, 934], "conf": 97.0}, {"text": "cost", "bbox": [758, 917, 805, 934], "conf": 96.0}, {"text": "of", "bbox": [813, 914, 834, 934], "conf": 96.0}, {"text": "replacing", "bbox": [842, 914, 952, 940], "conf": 96.0}, {"text": "the", "bbox": [959, 914, 996, 934], "conf": 96.0}, {"text": "locks.", "bbox": [1003, 914, 1067, 934], "conf": 96.0}, {"text": "On", "bbox": [1077, 915, 1108, 934], "conf": 97.0}, {"text": "the", "bbox": [1116, 914, 1153, 934], "conf": 96.0}, {"text": "expiration", "bbox": [1160, 916, 1281, 940], "conf": 96.0}, {"text": "of", "bbox": [1284, 910, 1301, 944], "conf": 96.0}, {"text": "this", "bbox": [1304, 914, 1361, 934], "conf": 96.0}, {"text": "Lease,", "bbox": [1370, 915, 1439, 937], "conf": 96.0}, {"text": "Tenant", "bbox": [302, 948, 385, 967], "conf": 96.0}, {"text": "shall", "bbox": [392, 947, 446, 967], "conf": 95.0}, {"text": "disclose", "bbox": [454, 947, 548, 967], "conf": 95.0}, {"text": "to", "bbox": [555, 950, 577, 967], "conf": 96.0}, {"text": "Landlord", "bbox": [587, 947, 693, 967], "conf": 96.0}, {"text": "the", "bbox": [700, 947, 737, 967], "conf": 96.0}, {"text": "combination", "bbox": [745, 947, 893, 967], "conf": 96.0}, {"text": "of", "bbox": [900, 947, 924, 967], "conf": 96.0}, {"text": "all", "bbox": [930, 947, 956, 967], "conf": 96.0}, {"text": "locks", "bbox": [964, 947, 1023, 967], "conf": 95.0}, {"text": "for", "bbox": [1031, 947, 1065, 967], "conf": 96.0}, {"text": "safes,", "bbox": [1072, 947, 1135, 970], "conf": 96.0}, {"text": "safe", "bbox": [1143, 947, 1189, 967], "conf": 96.0}, {"text": "cabinets", "bbox": [1197, 947, 1294, 967], "conf": 96.0}, {"text": "and", "bbox": [1302, 947, 1345, 967], "conf": 96.0}, {"text": "vault", "bbox": [1352, 947, 1411, 967], "conf": 96.0}, {"text": "doors,", "bbox": [1419, 947, 1490, 970], "conf": 96.0}, {"text": "if", "bbox": [302, 980, 319, 1000], "conf": 91.0}, {"text": "any,", "bbox": [324, 987, 370, 1006], "conf": 91.0}, {"text": "remaining", "bbox": [379, 982, 500, 1006], "conf": 96.0}, {"text": "in", "bbox": [507, 982, 529, 1000], "conf": 96.0}, {"text": "the", "bbox": [537, 980, 573, 1000], "conf": 96.0}, {"text": "Premises.", "bbox": [582, 981, 693, 1000], "conf": 95.0}, {"text": "5.", "bbox": [303, 1045, 321, 1064], "conf": 96.0}, {"text": "Landlord", "bbox": [330, 1044, 436, 1064], "conf": 96.0}, {"text": "reserves", "bbox": [444, 1051, 544, 1064], "conf": 95.0}, {"text": "the", "bbox": [552, 1044, 588, 1064], "conf": 95.0}, {"text": "right", "bbox": [596, 1044, 652, 1070], "conf": 96.0}, {"text": "to", "bbox": [660, 1047, 681, 1064], "conf": 96.0}, {"text": "exclude", "bbox": [690, 1044, 780, 1064], "conf": 96.0}, {"text": "from", "bbox": [787, 1044, 843, 1064], "conf": 96.0}, {"text": "the", "bbox": [851, 1044, 888, 1064], "conf": 96.0}, {"text": "Building", "bbox": [896, 1044, 995, 1070], "conf": 96.0}, {"text": "at", "bbox": [1001, 1047, 1023, 1064], "conf": 96.0}, {"text": "all", "bbox": [1031, 1044, 1057, 1064], "conf": 97.0}, {"text": "times", "bbox": [1065, 1046, 1129, 1064], "conf": 96.0}, {"text": "any", "bbox": [1137, 1051, 1179, 1070], "conf": 96.0}, {"text": "person", "bbox": [1186, 1051, 1267, 1070], "conf": 96.0}, {"text": "who", "bbox": [1275, 1044, 1324, 1064], "conf": 96.0}, {"text": "is", "bbox": [1333, 1046, 1350, 1064], "conf": 96.0}, {"text": "not", "bbox": [1358, 1047, 1397, 1064], "conf": 95.0}, {"text": "known", "bbox": [1404, 1044, 1484, 1064], "conf": 96.0}, {"text": "or", "bbox": [302, 1084, 327, 1097], "conf": 96.0}, {"text": "does", "bbox": [334, 1077, 388, 1097], "conf": 96.0}, {"text": "not", "bbox": [396, 1080, 434, 1097], "conf": 96.0}, {"text": "properly", "bbox": [442, 1077, 545, 1103], "conf": 96.0}, {"text": "identify", "bbox": [552, 1077, 642, 1103], "conf": 96.0}, {"text": "himself", "bbox": [650, 1077, 765, 1097], "conf": 80.0}, {"text": "to", "bbox": [742, 1073, 766, 1107], "conf": 80.0}, {"text": "the", "bbox": [774, 1077, 810, 1097], "conf": 96.0}, {"text": "Building", "bbox": [819, 1077, 917, 1103], "conf": 96.0}, {"text": "Manager.", "bbox": [925, 1078, 1031, 1103], "conf": 96.0}, {"text": "Landlord", "bbox": [1047, 1077, 1153, 1097], "conf": 96.0}, {"text": "may", "bbox": [1161, 1084, 1210, 1103], "conf": 96.0}, {"text": "at", "bbox": [1217, 1080, 1239, 1097], "conf": 93.0}, {"text": "its", "bbox": [1246, 1079, 1274, 1097], "conf": 93.0}, {"text": "option", "bbox": [1282, 1079, 1358, 1103], "conf": 97.0}, {"text": "require", "bbox": [1365, 1079, 1452, 1103], "conf": 96.0}, {"text": "all", "bbox": [1460, 1077, 1486, 1097], "conf": 96.0}, {"text": "persons", "bbox": [302, 1117, 395, 1136], "conf": 96.0}, {"text": "admitted", "bbox": [403, 1110, 509, 1130], "conf": 96.0}, {"text": "to", "bbox": [517, 1113, 538, 1130], "conf": 96.0}, {"text": "or", "bbox": [547, 1117, 572, 1130], "conf": 96.0}, {"text": "leaving", "bbox": [579, 1110, 664, 1136], "conf": 96.0}, {"text": "the", "bbox": [671, 1110, 708, 1130], "conf": 96.0}, {"text": "Building", "bbox": [716, 1110, 815, 1136], "conf": 96.0}, {"text": "to", "bbox": [821, 1113, 843, 1130], "conf": 96.0}, {"text": "register.", "bbox": [852, 1112, 948, 1136], "conf": 96.0}, {"text": "Tenant", "bbox": [956, 1111, 1039, 1130], "conf": 96.0}, {"text": "shall", "bbox": [1047, 1110, 1100, 1130], "conf": 96.0}, {"text": "be", "bbox": [1109, 1110, 1136, 1130], "conf": 96.0}, {"text": "responsible", "bbox": [1144, 1110, 1281, 1136], "conf": 96.0}, {"text": "for", "bbox": [1288, 1110, 1321, 1130], "conf": 95.0}, {"text": "all", "bbox": [1329, 1110, 1355, 1130], "conf": 96.0}, {"text": "persons", "bbox": [1364, 1117, 1457, 1136], "conf": 96.0}, {"text": "for", "bbox": [1465, 1110, 1498, 1130], "conf": 96.0}, {"text": "whom", "bbox": [302, 1142, 375, 1162], "conf": 82.0}, {"text": "it", "bbox": [383, 1144, 399, 1162], "conf": 93.0}, {"text": "authorizes", "bbox": [406, 1142, 530, 1162], "conf": 96.0}, {"text": "entry", "bbox": [538, 1145, 601, 1168], "conf": 96.0}, {"text": "into", "bbox": [608, 1144, 653, 1162], "conf": 96.0}, {"text": "the", "bbox": [661, 1142, 698, 1162], "conf": 96.0}, {"text": "Building", "bbox": [707, 1142, 805, 1168], "conf": 96.0}, {"text": "and", "bbox": [812, 1142, 855, 1162], "conf": 96.0}, {"text": "shall", "bbox": [862, 1142, 916, 1162], "conf": 96.0}, {"text": "be", "bbox": [924, 1142, 952, 1162], "conf": 96.0}, {"text": "liable", "bbox": [959, 1142, 1023, 1162], "conf": 96.0}, {"text": "to", "bbox": [1031, 1145, 1052, 1162], "conf": 96.0}, {"text": "Landlord", "bbox": [1062, 1142, 1168, 1162], "conf": 96.0}, {"text": "for", "bbox": [1176, 1142, 1209, 1162], "conf": 95.0}, {"text": "all", "bbox": [1216, 1142, 1242, 1162], "conf": 94.0}, {"text": "acts", "bbox": [1251, 1145, 1296, 1162], "conf": 96.0}, {"text": "of", "bbox": [1304, 1142, 1328, 1162], "conf": 96.0}, {"text": "such", "bbox": [1334, 1142, 1386, 1162], "conf": 96.0}, {"text": "persons.", "bbox": [1395, 1149, 1492, 1168], "conf": 96.0}, {"text": "A", "bbox": [1046, 2595, 1070, 2617], "conf": 95.0}, {"text": "Glimmer", "bbox": [1080, 2594, 1208, 2618], "conf": 95.0}, {"text": "of", "bbox": [1217, 2594, 1247, 2617], "conf": 96.0}, {"text": "Hope", "bbox": [1253, 2595, 1327, 2624], "conf": 96.0}, {"text": "Foundation", "bbox": [1337, 2594, 1500, 2617], "conf": 96.0}, {"text": "January", "bbox": [1275, 2633, 1392, 2662], "conf": 96.0}, {"text": "1,", "bbox": [1404, 2633, 1426, 2661], "conf": 95.0}, {"text": "2022", "bbox": [1436, 2632, 1500, 2655], "conf": 95.0}]}